microclient/__init__.py
microclient/bases.py
microclient/response.py
microclient/utils.py
microclient-0.7.6.dist-info/LICENSE
microclient-0.7.6.dist-info/METADATA
microclient-0.7.6.dist-info/WHEEL
microclient-0.7.6.dist-info/top_level.txt
microclient-0.7.6.dist-info/RECORD
