Metadata-Version: 2.1
Name: microclient
Version: 0.7.6
Summary: A library for creating REST API clients quick and painless.
Home-page: https://bitbucket.org/biinsight/microclient/
Author: Szymon Nowak
Author-email: snowak@biinsight.pl
License: UNKNOWN
Platform: UNKNOWN
Classifier: Programming Language :: Python :: 3
Classifier: Programming Language :: Python :: 3.4
Classifier: Programming Language :: Python :: 3.5
Requires-Dist: requests
Requires-Dist: loguru
